fluidgrids_common/__init__.py
fluidgrids_common/server.py
fluidgrids_common/utils/__init__.py
fluidgrids_common/utils/adapter.py
fluidgrids_common/utils/credential.py
fluidgrids_common/utils/main.py
fluidgrids_common/utils/nats.py
fluidgrids_common/utils/node.py
fluidgrids_common/utils/otel_config.py
fluidgrids_common-0.3.0.dist-info/licenses/LICENSE
fluidgrids_common-0.3.0.dist-info/METADATA
fluidgrids_common-0.3.0.dist-info/WHEEL
fluidgrids_common-0.3.0.dist-info/top_level.txt
fluidgrids_common-0.3.0.dist-info/RECORD
