Metadata-Version: 2.4
Name: fluidgrids-common
Version: 0.3.0
Summary: Common utilities for Fluidgrids backend nodes
Author-email: Fluidgrids Team <info@algoshred.com>
License: MIT
Project-URL: Homepage, https://github.com/algoshred/fluidgrids-common
Project-URL: Bug Tracker, https://github.com/algoshred/fluidgrids-common/issues
Classifier: Programming Language :: Python :: 3
Classifier: Programming Language :: Python :: 3.9
Classifier: Programming Language :: Python :: 3.10
Classifier: Programming Language :: Python :: 3.11
Classifier: License :: OSI Approved :: MIT License
Classifier: Operating System :: OS Independent
Requires-Python: >=3.9
License-File: LICENSE
Requires-Dist: ariadne==0.26.2
Requires-Dist: nats-py==2.10.0
Requires-Dist: websockets==15.0.1
Requires-Dist: opentelemetry-api==1.33.0
Requires-Dist: opentelemetry-sdk==1.33.0
Requires-Dist: opentelemetry-exporter-otlp-proto-grpc==1.33.0
Requires-Dist: opentelemetry-exporter-otlp-proto-http==1.33.0
Requires-Dist: opentelemetry-instrumentation-fastapi==0.54b0
Requires-Dist: opentelemetry-instrumentation-httpx==0.54b0
Requires-Dist: opentelemetry-instrumentation-requests==0.54b0
Requires-Dist: opentelemetry-instrumentation-logging==0.54b0
Requires-Dist: python-dotenv==1.1.0
Requires-Dist: fastapi==0.115.12
Requires-Dist: uvicorn==0.34.2
Requires-Dist: pydantic-core==2.33.2
Requires-Dist: pydantic-settings==2.9.1
Requires-Dist: watchfiles==1.0.5
Requires-Dist: httpx==0.27.0
Dynamic: license-file
